pyturbseq/__init__.py
pyturbseq/calling.py
pyturbseq/cellranger.py
pyturbseq/de.py
pyturbseq/guides.py
pyturbseq/interaction.py
pyturbseq/plot.py
pyturbseq/utils.py
pyturbseq-0.1.0.dist-info/licenses/LICENSE
pyturbseq-0.1.0.dist-info/METADATA
pyturbseq-0.1.0.dist-info/WHEEL
pyturbseq-0.1.0.dist-info/top_level.txt
pyturbseq-0.1.0.dist-info/RECORD
