Metadata-Version: 2.4
Name: pyturbseq
Version: 0.1.0
Summary: A Python package for perturbational single-cell data analysis
Author-email: Aidan Winters <aidanw@arcinstitute.org>
Project-URL: repository, https://github.com/aidanwinters/pyturbseq
Requires-Python: <3.14,>=3.9
License-File: LICENSE
Requires-Dist: scanpy>=1.9.0
Requires-Dist: scipy<=1.15.3,>=1.8.0
Requires-Dist: scikit-learn>=1.0.0
Requires-Dist: umap-learn>=0.5.0
Requires-Dist: numpy>=1.22.0
Requires-Dist: pandas>=1.4.0
Requires-Dist: matplotlib>=3.5.0
Requires-Dist: seaborn>=0.11.0
Requires-Dist: tqdm>=4.60.0
Requires-Dist: fastcluster>=1.2.0
Requires-Dist: adjusttext>=0.7.0
Requires-Dist: pydeseq2>=0.3.0
Requires-Dist: statsmodels>=0.14.0
Requires-Dist: adpbulk>=0.1.0
Requires-Dist: anndata>=0.8.0
Requires-Dist: hdbscan>=0.8.0
Requires-Dist: dcor>=0.5.0
Requires-Dist: upsetplot>=0.6.0
Requires-Dist: joblib>=1.0.0
Provides-Extra: test
Requires-Dist: pytest>=7.0.0; extra == "test"
Requires-Dist: pytest-cov>=4.0.0; extra == "test"
Requires-Dist: pytest-mock>=3.10.0; extra == "test"
Provides-Extra: dev
Requires-Dist: black>=22.0.0; extra == "dev"
Requires-Dist: isort>=5.10.0; extra == "dev"
Requires-Dist: flake8>=4.0.0; extra == "dev"
Requires-Dist: mypy>=0.950; extra == "dev"
Requires-Dist: pre-commit>=3.0.0; extra == "dev"
Provides-Extra: docs
Requires-Dist: sphinx>=5.0.0; extra == "docs"
Requires-Dist: sphinx-rtd-theme>=1.2.0; extra == "docs"
Requires-Dist: myst-parser>=0.18.0; extra == "docs"
Requires-Dist: sphinx-autodoc-typehints>=1.19.0; extra == "docs"
Dynamic: license-file
